local_qwen3b_part027/__init__.py
local_qwen3b_part027/qwen2.5-3b-instruct-q5_k_m.gguf.part_027
local_qwen3b_part027-0.0.1.dist-info/METADATA
local_qwen3b_part027-0.0.1.dist-info/WHEEL
local_qwen3b_part027-0.0.1.dist-info/top_level.txt
local_qwen3b_part027-0.0.1.dist-info/RECORD
